neurovista/__init__.py
neurovista/neurovista.py
neurovista-0.1.1.dist-info/LICENSE
neurovista-0.1.1.dist-info/METADATA
neurovista-0.1.1.dist-info/WHEEL
neurovista-0.1.1.dist-info/RECORD
