Metadata-Version: 2.1
Name: neurovista
Version: 0.1.1
Summary: Python package for plotting neural morpholgies with PyVista.
Home-page: https://github.com/CAVEconnectome/neurovista
License: MIT
Author: Ben Pedigo
Author-email: ben.pedigo@alleninstitute.org
Requires-Python: >=3.11.0,<3.12.0
Classifier: Development Status :: 2 - Pre-Alpha
Classifier: Intended Audience :: Developers
Classifier: License :: OSI Approved :: MIT License
Classifier: Natural Language :: English
Classifier: Programming Language :: Python :: 3
Classifier: Programming Language :: Python :: 3.11
Requires-Dist: beartype (>=0.16.4,<0.17.0)
Requires-Dist: pyvista[jupyter] (>=0.43.3,<0.44.0)
